jj2c/__init__.py
jj2c/sql_templating.py
jj2c-0.2.1.data/scripts/jj2c
jj2c-0.2.1.dist-info/LICENSE.md
jj2c-0.2.1.dist-info/METADATA
jj2c-0.2.1.dist-info/WHEEL
jj2c-0.2.1.dist-info/top_level.txt
jj2c-0.2.1.dist-info/RECORD
